_ma_playback.abi3.so
just_playback/playback.py
just_playback/ma_result.py
just_playback/__init__.py
just_playback-0.1.8.dist-info/RECORD
just_playback-0.1.8.dist-info/LICENSE
just_playback-0.1.8.dist-info/WHEEL
just_playback-0.1.8.dist-info/top_level.txt
just_playback-0.1.8.dist-info/METADATA
