Metadata-Version: 2.1
Name: just_playback
Version: 0.1.8
Summary: A small package for playing audio in python                     with file format independent methods for playback control
Home-page: https://github.com/cheofusi/just_playback
Author: Cheo Fusi
Author-email: fusibrandon13@gmail.com
License: MIT
Keywords: audio,music,wave,wavmp3,media,song,play,player,playback,audioplayer,mp3player
Classifier: Development Status :: 3 - Alpha
Classifier: Intended Audience :: Developers
Classifier: Intended Audience :: Education
Classifier: Topic :: Multimedia
Classifier: Topic :: Multimedia :: Sound/Audio
Classifier: Topic :: Multimedia :: Sound/Audio :: Players
Classifier: Topic :: Multimedia :: Sound/Audio :: Players :: MP3
Classifier: License :: OSI Approved :: MIT License
Classifier: Programming Language :: Python :: 3.6
Classifier: Programming Language :: Python :: 3.7
Classifier: Programming Language :: Python :: 3.8
Classifier: Programming Language :: Python :: 3.9
Classifier: Programming Language :: Python :: 3.10
Classifier: Programming Language :: Python :: 3.11
Classifier: Programming Language :: Python :: 3.12
License-File: LICENSE
Requires-Dist: cffi >=1.0.0
Requires-Dist: tinytag
